Metadata-Version: 2.4
Name: catalyst-pack-schemas
Version: 1.0.0
Summary: Shared schemas and validation for Catalyst Knowledge Packs
Author-email: Catalyst Team <team@catalyst.dev>
License: MIT
Project-URL: Homepage, https://github.com/your-org/catalyst-pack-schemas
Project-URL: Repository, https://github.com/your-org/catalyst-pack-schemas
Project-URL: Issues, https://github.com/your-org/catalyst-pack-schemas/issues
Classifier: Development Status :: 4 - Beta
Classifier: Intended Audience :: Developers
Classifier: License :: OSI Approved :: MIT License
Classifier: Programming Language :: Python :: 3
Classifier: Programming Language :: Python :: 3.8
Classifier: Programming Language :: Python :: 3.9
Classifier: Programming Language :: Python :: 3.10
Classifier: Programming Language :: Python :: 3.11
Requires-Dist: pydantic>=2.0.0
Requires-Dist: pyyaml>=6.0
Requires-Dist: jsonschema>=4.0.0
Requires-Dist: requests>=2.25.0
Requires-Dist: pathlib>=1.0.0; python_version < "3.4"
Provides-Extra: dev
Requires-Dist: pytest>=7.0.0; extra == "dev"
Requires-Dist: black>=22.0.0; extra == "dev"
Requires-Dist: isort>=5.0.0; extra == "dev"
Requires-Dist: mypy>=1.0.0; extra == "dev"
